Medical_Image_Plot/__init__.py
Medical_Image_Plot/vtk_plot.py
Plot_3D_Medical_Image-0.0.1.dist-info/METADATA
Plot_3D_Medical_Image-0.0.1.dist-info/WHEEL
Plot_3D_Medical_Image-0.0.1.dist-info/top_level.txt
Plot_3D_Medical_Image-0.0.1.dist-info/RECORD
